Metadata-Version: 1.1
Name: microcollections
Version: 0.0.5
Summary: Declarative dictionary-based model classes for Python
Home-page: https://github.com/zbyte64/micromodels-collections/
Author: UNKNOWN
Author-email: UNKNOWN
License: Public Domain
Platform: UNKNOWN
Classifier: Programming Language :: Python
Classifier: Development Status :: 3 - Alpha
Classifier: Intended Audience :: Developers
Classifier: License :: Public Domain
Classifier: Operating System :: OS Independent
Classifier: Topic :: Software Development :: Libraries :: Python Modules
